ndimage_enaml/__init__.py
ndimage_enaml/gui.enaml
ndimage_enaml/model.py
ndimage_enaml/presenter.py
ndimage_enaml/sphere.py
ndimage_enaml/util.py
ndimage_enaml/version.py
ndimage_enaml-0.0.11.dist-info/METADATA
ndimage_enaml-0.0.11.dist-info/WHEEL
ndimage_enaml-0.0.11.dist-info/top_level.txt
ndimage_enaml-0.0.11.dist-info/RECORD
