Metadata-Version: 2.4
Name: ndimage-enaml
Version: 0.0.11
Summary: Common tools for creating interactive views of ND images in Enaml
Author-email: Brad Buran <buran@ohsu.edu>
Maintainer-email: Brad Buran <buran@ohsu.edu>
Requires-Python: >=3.7
Requires-Dist: atom
Requires-Dist: enaml[qt6-pyside]
Requires-Dist: matplotlib
Requires-Dist: numpy
